pythonvideoannotator_module_findorientation/__init__.py
pythonvideoannotator_module_findorientation/findorientation_window.py
pythonvideoannotator_module_findorientation/module.py
Python_video_annotator_module_find_orientation-0.5.18.dist-info/METADATA
Python_video_annotator_module_find_orientation-0.5.18.dist-info/WHEEL
Python_video_annotator_module_find_orientation-0.5.18.dist-info/top_level.txt
Python_video_annotator_module_find_orientation-0.5.18.dist-info/RECORD
